YushenDuihua1to5/Dockerfile
YushenDuihua1to5/README.md
YushenDuihua1to5/__init__.py
YushenDuihua1to5/__main__.py
YushenDuihua1to5/file.epub
YushenDuihua1to5/index.html
YushenDuihua1to5/css/__init__.py
YushenDuihua1to5/css/annotations.css
YushenDuihua1to5/css/main.css
YushenDuihua1to5/css/normalize.css
YushenDuihua1to5/css/popup.css
YushenDuihua1to5/font/__init__.py
YushenDuihua1to5/font/fontello.eot
YushenDuihua1to5/font/fontello.svg
YushenDuihua1to5/font/fontello.ttf
YushenDuihua1to5/font/fontello.woff
YushenDuihua1to5/img/__init__.py
YushenDuihua1to5/img/annotator-glyph-sprite.png
YushenDuihua1to5/img/annotator-icon-sprite.png
YushenDuihua1to5/img/apple-touch-icon.png
YushenDuihua1to5/img/cancelfullscreen.png
YushenDuihua1to5/img/close.png
YushenDuihua1to5/img/fullscreen.png
YushenDuihua1to5/img/loader.gif
YushenDuihua1to5/img/menu-icon.png
YushenDuihua1to5/img/save.png
YushenDuihua1to5/img/saved.png
YushenDuihua1to5/img/settings-s.png
YushenDuihua1to5/img/settings.png
YushenDuihua1to5/img/star.png
YushenDuihua1to5/js/__init__.py
YushenDuihua1to5/js/epub.js
YushenDuihua1to5/js/epub.min.js
YushenDuihua1to5/js/epub.min.map
YushenDuihua1to5/js/hooks.min.js
YushenDuihua1to5/js/hooks.min.map
YushenDuihua1to5/js/reader.js
YushenDuihua1to5/js/reader.js.map
YushenDuihua1to5/js/reader.min.js
YushenDuihua1to5/js/reader.min.map
YushenDuihua1to5/js/hooks/__init__.py
YushenDuihua1to5/js/hooks/extensions/__init__.py
YushenDuihua1to5/js/hooks/extensions/highlight.js
YushenDuihua1to5/js/libs/__init__.py
YushenDuihua1to5/js/libs/jquery.min.js
YushenDuihua1to5/js/libs/localforage.min.js
YushenDuihua1to5/js/libs/screenfull.js
YushenDuihua1to5/js/libs/screenfull.min.js
YushenDuihua1to5/js/libs/zip.min.js
YushenDuihua1to5/js/plugins/__init__.py
YushenDuihua1to5/js/plugins/hypothesis.js
YushenDuihua1to5/js/plugins/search.js
yushen_duihua_1to5-2022.10.3.0.dist-info/METADATA
yushen_duihua_1to5-2022.10.3.0.dist-info/WHEEL
yushen_duihua_1to5-2022.10.3.0.dist-info/entry_points.txt
yushen_duihua_1to5-2022.10.3.0.dist-info/top_level.txt
yushen_duihua_1to5-2022.10.3.0.dist-info/RECORD
